pylinq/__init__.py
pylinqlib-1.1.2.dist-info/LICENSE
pylinqlib-1.1.2.dist-info/METADATA
pylinqlib-1.1.2.dist-info/WHEEL
pylinqlib-1.1.2.dist-info/top_level.txt
pylinqlib-1.1.2.dist-info/RECORD
