Metadata-Version: 2.1
Name: pylinqlib
Version: 1.1.2
Summary: LINQ implementation
Home-page: UNKNOWN
Author: crimsondevel
Author-email: crimsondevel@gmail.com
License: UNKNOWN
Platform: UNKNOWN
Classifier: Programming Language :: Python :: 3
Classifier: License :: OSI Approved :: MIT License
Classifier: Operating System :: OS Independent
Requires-Python: >=3.8
License-File: LICENSE
